{
  "String1": "Language detected:",
  "String2": "Note: If your language is not on the website, it is changed by default to English.",
  "String3": "If your language is different from the one detected by the website, you can change it here:",
  "String4": "Change language",
  "String5": "Please refresh the page to fully apply the language change",
  "String6": "You can also select which language you want the game translations to appear in if they are available:",
  "String7": "Language on the web",
  "String8": "Translations in games"
}
