{
  "Title": "Tienda",
  "String1": "tienes {0} Pepe Coins para gastar",
  "String2": "Juegos Disponibles",
  "String3": "Historial",
  "Daily": "Entrada diaria",
  "Buy2": "Adquirido",
  "Buy": "¿Estás seguro de adquirir {0}?",
  "Yes": "Si",
  "No": "No",
  "Close": "Cerrar",
  "Redeem": "Canjear en Steam",
  "Poor": "No tienes las suficientes Pepe Coins para adquirir {0}.",
  "Problem": "Todos estos juegos proceden de bundles de Humble Bundle y Fanatical, pero si tenéis algún problema con la clave mandar un correo a admin@pepeizqdeals.com para que os devuelva las Pepe Coins que gastéis.",
  "Limit": "Has llegado al limite de 30 Pepe Coins en la cuenta, si gastas Pepe Coins en cualquier juego volverás a ganar coins cada día."
}