{
  "Title": "Pacotes",
  "Subtitle": "Confira todos os pacotes de jogos para PC que estão disponíveis atualmente.",
  "String1": "Pacotes disponíveis",
  "String2": "Arquivo de pacotes",
  "String3": "Abrir pacote",
  "String4": "Este pacote termina em {0} dias",
  "String5": "Este pacote termina em {0} dia",
  "String6": "Este pacote termina hoje",
  "String7": "Este pacote terminou",
  "String8": "jogos",
  "String9": "Preço Mínimo",
  "String10": "Pacotes",
  "String11": "Livre",
  "String12": "Assinaturas",
  "String14": "Custo mínimo comprando separadamente",
  "String15": "DLC",
  "String16": "{0} pacote disponível para compra",
  "String17": "{0} pacotes disponíveis para compra",
  "String18": "Não há pacotes disponíveis para compra",
  "String20": "por unidade",
  "String21": "jogo",
  "String22": "Pacote dividido em vários níveis e disponível em",
  "String23": "Pacote onde você pode escolher os jogos e disponíveis",
  "String24": "Primeira vez no pacote",
  "String25": "Low histórico:",
  "String26": "Pacote aberto",
  "String27": "1 DLC",
  "String28": "{0} DLCs"
}